[
  {"order_id":"a1b2c3d4-e5f6-7890-abcd-ef1234567890","product_id":"PROD-0001","product_name":"Wireless Bluetooth Headphones","category":"Electronics","quantity":2,"unit_price":79.99,"total_amount":159.98,"store_id":"STORE-001","store_name":"RetailMart #1","region":"Northeast","state":"NY","city":"Albany","payment_method":"credit_card","customer_segment":"premium","transaction_timestamp":"2024-06-15T10:30:00","event_type":"purchase"},
  {"order_id":"b2c3d4e5-f6a7-8901-bcde-f12345678901","product_id":"PROD-0003","product_name":"Premium Ground Coffee 12oz","category":"Groceries","quantity":5,"unit_price":12.49,"total_amount":62.45,"store_id":"STORE-003","store_name":"RetailMart #3","region":"Midwest","state":"IL","city":"Springfield","payment_method":"debit_card","customer_segment":"regular","transaction_timestamp":"2024-06-15T11:15:00","event_type":"purchase"},
  {"order_id":"c3d4e5f6-a7b8-9012-cdef-123456789012","product_id":"PROD-0005","product_name":"Running Shoes Pro","category":"Sports","quantity":1,"unit_price":129.99,"total_amount":129.99,"store_id":"STORE-005","store_name":"RetailMart #5","region":"West","state":"CA","city":"Sacramento","payment_method":"mobile_pay","customer_segment":"loyalty","transaction_timestamp":"2024-06-15T09:45:00","event_type":"purchase"},
  {"order_id":"d4e5f6a7-b8c9-0123-defa-234567890123","product_id":"PROD-0010","product_name":"Multivitamin 90ct","category":"Health","quantity":3,"unit_price":22.99,"total_amount":68.97,"store_id":"STORE-007","store_name":"RetailMart #7","region":"Southeast","state":"GA","city":"Savannah","payment_method":"cash","customer_segment":"new","transaction_timestamp":"2024-06-15T14:20:00","event_type":"purchase"},
  {"order_id":"e5f6a7b8-c9d0-1234-efab-345678901234","product_id":"PROD-0012","product_name":null,"category":null,"quantity":1,"unit_price":59.99,"total_amount":59.99,"store_id":"STORE-004","store_name":"RetailMart #4","region":"Southwest","state":"TX","city":"Austin","payment_method":"credit_card","customer_segment":"regular","transaction_timestamp":"2024-06-14T22:05:00","event_type":"purchase"}
]
